edulib/__init__.py
edulib/config.py
edulib/core/__init__.py
edulib/core/apps.py
edulib/core/unit_of_work.py
edulib/core/academic_years/__init__.py
edulib/core/academic_years/apps.py
edulib/core/academic_years/models.py
edulib/core/academic_years/adapters/__init__.py
edulib/core/academic_years/adapters/db.py
edulib/core/academic_years/domain/__init__.py
edulib/core/academic_years/domain/events.py
edulib/core/academic_years/domain/factories.py
edulib/core/academic_years/domain/model.py
edulib/core/academic_years/domain/services.py
edulib/core/academic_years/migrations/0001_initial.py
edulib/core/academic_years/migrations/0002_alter_academicyear_code.py
edulib/core/academic_years/migrations/0003_remove_academicyear_id_and_more.py
edulib/core/academic_years/migrations/0004_auto_20240808_1508.py
edulib/core/academic_years/migrations/0005_alter_academicyear_id.py
edulib/core/academic_years/migrations/__init__.py
edulib/core/academic_years/services/__init__.py
edulib/core/academic_years/services/handlers.py
edulib/core/academic_years/tests/__init__.py
edulib/core/academic_years/tests/test_services.py
edulib/core/academic_years/tests/utils.py
edulib/core/adapters/__init__.py
edulib/core/adapters/db.py
edulib/core/address/__init__.py
edulib/core/address/apps.py
edulib/core/address/models.py
edulib/core/address/adapters/__init__.py
edulib/core/address/adapters/db.py
edulib/core/address/domain/__init__.py
edulib/core/address/domain/commands.py
edulib/core/address/domain/factories.py
edulib/core/address/domain/model.py
edulib/core/address/domain/services.py
edulib/core/address/migrations/0001_initial.py
edulib/core/address/migrations/__init__.py
edulib/core/address/services/__init__.py
edulib/core/address/services/handlers.py
edulib/core/address/services/validators.py
edulib/core/address/tests/__init__.py
edulib/core/address/tests/test_services.py
edulib/core/address/tests/utils.py
edulib/core/base/__init__.py
edulib/core/base/domain.py
edulib/core/base/files.py
edulib_core-0.14.0.dist-info/METADATA
edulib_core-0.14.0.dist-info/WHEEL
edulib_core-0.14.0.dist-info/top_level.txt
edulib_core-0.14.0.dist-info/RECORD
